swarmauri_evaluator_anyusage/AnyTypeUsageEvaluator.py
swarmauri_evaluator_anyusage/__init__.py
swarmauri_evaluator_anyusage-0.1.2.dist-info/LICENSE
swarmauri_evaluator_anyusage-0.1.2.dist-info/METADATA
swarmauri_evaluator_anyusage-0.1.2.dist-info/WHEEL
swarmauri_evaluator_anyusage-0.1.2.dist-info/entry_points.txt
swarmauri_evaluator_anyusage-0.1.2.dist-info/RECORD
